MANIFEST.in
README.rst
setup.py
factorialexample.egg-info/PKG-INFO
factorialexample.egg-info/SOURCES.txt
factorialexample.egg-info/dependency_links.txt
factorialexample.egg-info/top_level.txt
myfact/__init__.py
myfact/fact.py