Metadata-Version: 1.0
Name: factorialexample
Version: 1.0.0
Summary: Factorial module.
Home-page: http://pymbook.readthedocs.org/en/latest/
Author: yeching
Author-email: yq08051035@163.com
License: MIT
Platform: Linux
